README.md
setup.cfg
setup.py
cloudomate/__init__.py
cloudomate/config.py
cloudomate/handlers.py
cloudomate/options.py
cloudomate/scripts.py
cloudomate/server.py
cloudomate/servers.py
cloudomate/util.py
cloudomate_thecloudgarage.egg-info/PKG-INFO
cloudomate_thecloudgarage.egg-info/SOURCES.txt
cloudomate_thecloudgarage.egg-info/dependency_links.txt
cloudomate_thecloudgarage.egg-info/entry_points.txt
cloudomate_thecloudgarage.egg-info/not-zip-safe
cloudomate_thecloudgarage.egg-info/requires.txt
cloudomate_thecloudgarage.egg-info/top_level.txt